matterbabble/__init__.py
matterbabble/__main__.py
matterbabble/application.py
matterbabble/consts.py
matterbabble/discourse.py
matterbabble/images.py
matterbabble/matterbridge.py
matterbabble/service.py
matterbabble-1.0.1.dist-info/LICENSE
matterbabble-1.0.1.dist-info/METADATA
matterbabble-1.0.1.dist-info/WHEEL
matterbabble-1.0.1.dist-info/entry_points.txt
matterbabble-1.0.1.dist-info/top_level.txt
matterbabble-1.0.1.dist-info/RECORD
