Metadata-Version: 2.1
Name: matterbabble
Version: 1.0.1
Summary: Connect Discourse threads to Matterbridge.
Home-page: https://github.com/DeclanHoare/matterbabble
Author: Declan Hoare
Author-email: declanhoare@exemail.com.au
License: UNKNOWN
Platform: UNKNOWN
Classifier: Programming Language :: Python :: 3
Classifier: License :: OSI Approved :: Apache Software License
Classifier: Operating System :: OS Independent
Requires-Dist: aiohttp
Requires-Dist: bidict
Requires-Dist: commonmark
Requires-Dist: commonmarkextensions
